ignition_kernel/__init__.py
ignition_kernel/__main__.py
ignition_kernel/provisioner.py
ignition_kernel-1.0.0.dist-info/LICENSE
ignition_kernel-1.0.0.dist-info/METADATA
ignition_kernel-1.0.0.dist-info/WHEEL
ignition_kernel-1.0.0.dist-info/entry_points.txt
ignition_kernel-1.0.0.dist-info/top_level.txt
ignition_kernel-1.0.0.dist-info/RECORD
