Metadata-Version: 2.1
Name: ignition-kernel
Version: 1.0.0
Summary: Jupyter kernel provisioner for connecting to an Ignition instance.
Author-email: Andrew Geiger <andrew@corsosystems.com>
Project-URL: Homepage, https://github.com/ignition-kernel/kernel-provisioner
Project-URL: Source, https://github.com/ignition-kernel/kernel-provisioner
Classifier: Development Status :: 4 - Beta
Classifier: Programming Language :: Python :: 3
Classifier: License :: OSI Approved :: Apache Software License
Classifier: Operating System :: OS Independent
Requires-Python: >=3.6.1
License-File: LICENSE
